{"rate_limit": 1, "expires_in": 300, "api_latest_version": "1.2", "generated_on": "2015-03-23T05:10:45+00:00", "data": {"4057367": "oz}sD`riuN@q@lVam@", "4053675": "}}}sD|uquNAkJ@gHsA?KCGGCMHuC", "4097095": "kp~sDttnuNCnOaC?", "4057299": "mt}sDlnkuN?[qJG", "4025863": "{d}sDv`puN{DD_J@", "4064579": "_vbtDdrzuNXcAvCoIp@_BrFsOlG}RxDqK|H{S|CwI^mARuADiADaFCuF@}WCuCB{KAqJBaABwxABgT", "4044299": "sn_tD|zpuNq@HiEAm@I", "4057555": "ml{sDt_suNaHeY", "4044303": "wu}sD~`puNqID", "4057879": "kl~sDhqpuN?iI", "4106679": "uk~sD~tmuNF\\?tAGV", "4044547": "}r~sDh{puNp@G`DJ", "4105923": "wc_tD~|quNuD@mDCoJ?H}NCsEb@eFDgB?a@", "4025879": "q_}sDpepuNAbG", "4044463": "{`~sDvnpuNMCEODMLE", "4044319": "wu}sD~mpuN?~KMZ", "4097075": "mt~sDttnuN`C?", "4080535": "agatDfbluNFqOAqJB_EAuDBcOBgDAuHDyH", "4044323": "s_}sDtmpuN?bM", "4105395": "mc}sDrsmuNCOMKQA}BBc@D", "4061095": "mi}sD|tmuNKGGM@a@", "4041223": "s_}sDhxouN?jG", "4066643": "{h`tDrdiuNIOIEKAQFGN?RDLHFBbAG~EId@SXUVyA`Ai@b@a@l@y@tB", "4044295": "sn_tD|zpuNq@KiE?m@H", "4044335": "sd}sDx{puN~C?", "4067635": "iq_tDzmpuNkDAoBJd@`GBz@?vA", "4044339": "gf{sDbrnuNc@t@]|@WhAQ~AgA``@CbCPnFPtG@~A?pG", "4077063": "kz_tDlbluNie@AkEC", "4057143": "sn_tD|zpuNA_LsAA", "4080419": "__}sD|dquN@cAAgA", "4097083": "ae}sDtjjuNCxU@bKCdf@Df@L^VjAv@|H", "4049987": "iu}sDvqmuNyC?gFF", "4057159": "yz~sDpckuNa@KuAy@]a@", "4057915": "_r`tDp~iuNYa@EQCS?Q", "4067667": "gl~sDvfouNcJCoDB{D?", "4016823": "qa}sDbpmuNCQLcBAK@MDI", "4077027": "igatD`_nuNBqO", "4105995": "__}sDp`quNE_A", "4057171": "mfatDpqiuNiJqF_JqFkVuN", "4057779": "{s`tDh}iuNz@f@", "4057839": "gl~sDvfouNCv\\", "4066815": "i}|sDx{puNiA?", "4080727": "_ubtDlfouNvUJdx@JnF?fBE", "4068111": "sa}sDlqmuNBz@LpAbApEf@vDk@EgUD", "4075623": "wi}sDzuquNmEBwLA", "4044387": "i`~sDdapuNCHCFMB", "4101527": "mszsDviluNdAtDR\\TbAHj@`@dBZx@d@l@h@d@h@^T\\DZMh@Yv@[b@UJa@Ao@]m@c@k@k@]q@u@wB}@\\e@V_At@_@`@rBzBlAdAbAv@tAz@r@`@vLdGKV", "4044391": "{`~sDnmpuNCsJ", "4044311": "ud~sDx{puNcAKoD?", "4066611": "y{`tDd_nuNpJBlNCv@Bp@Lv@VzAt@", "4041087": "s_}sDt`puN@zC", "4044395": "}`~sDn`puNIBEDAJ@HDFFB", "4077679": "{}}sDp}quNqMD", "4080455": "g_}sDjkruN{@A", "4044307": "ud~sDx{puNtB?", "4057771": "sy_tDxnjuNk@GsBcAkCyAgPsJ", "4057471": "kl~sDhqpuNIZ?l@HX", "4059259": "{x_tDzzpuNwm@C", "4078707": "ilzsDljjuN{OFod@?AyDDua@uY?Clg@uF@", "4106063": "ak~sDdpiuNCjY", "4056939": "igatD`_nuNeCA}CIyAQ_Ci@_C{@}QuIqEoB", "4057883": "kl~sDndpuNHT?b@IT", "4066595": "s_}sDx{puNLvA", "4044427": "sgatDvzpuNGhD?lS", "4044431": "aoatDtzpuNlF@", "4080439": "im{sDx_suNwGaY", "4057539": "yb~sDxfouNd@H", "4099523": "ga~sDhbnuNBpVBrCAbE", "4016791": "_`}sDhkmuNFPAN", "4057355": "sk~sDjbnuNjIA", "4016795": "o}|sDlkmuNiA\\", "4105399": "mi}sD|tmuNhAApA@TGJO@Q", "4067039": "}f~sDpjjuNrK?", "4016799": "y_}sDjlmuNEHIDG@KZGx@KN", "4016803": "g`}sDdkmuNFB", "4057543": "sa~sDbgouNDD", "4016807": "o}|sDlkmuNo@@_@E", "4016811": "aa}sDhkmuNNEH@", "4073859": "s_}sDhxouNeD@AjG", "4016815": "cb}sDjcmuNJHb@fEJf@", "4080423": "__}sD|dquNE`P", "4016819": "cb}sDjcmuN?N^dE@f@", "4044467": "k`~sDbnpuNCLKD", "4044471": "{`~sDnmpuNHBDN", "4044475": "}`~sDn`puNNFBL", "4080443": "av{sDveruNmCoK", "4067051": "sy_tDxnjuNNyDBaDAyD@{L", "4057919": "}r`tDbziuNk@n@KFKDU?", "4057291": "ws~sDfhkuNf@LjB~@fBr@|CZ|EB", "4057527": "sa~sDbgouN?O@E", "4105927": "{k~sDfpiuNkDDyJ?kJBcHCyE?SE", "4105931": "{k~sDfpiuNXA", "4080767": "mfatDtpiuNtOjJ", "4018039": "iu}sDvqmuN?lO", "4057775": "sy_tDxnjuNn@XrOfJ", "4057783": "{s`tDh}iuNVq@", "4041423": "yy_tD|aluNHDBH", "4056867": "og_tDzzjuN^HzA|@RV", "4080259": "g_}sDjkruNlF@fACx@K~@Sp@WzAs@d@OXE^GpEYf@FpAEn@@", "4067031": "y{`tDd_nuNoJC", "4056795": "wk~sD`rmuNjIA", "4056799": "uk~sD`mmuNA~C", "4044315": "wu}sD~mpuNsIB", "4057903": "_`~sDdnkuNpJF", "4049635": "s_}sDtmpuNgD@", "4077015": "qtzsDnfluNfAg@VUJ[D_A@mEFg@La@d@u@Te@Lq@@iECoD@wUBs@Jg@L]\\k@VY", "4057835": "sk~sDjbnuNApEGtEEpSCpA", "4080459": "ca}sDhkruNg@IOGSOIKEOMk@?uCEu@_AqC}AcEEa@", "4056811": "av{sDveruNaAXg@F[?eCO", "4056727": "uk~sD`mmuNI_@B}H?{JHq@", "4105979": "yizsDnjjuN`@ArC?|@Blu@AlI@pS@`@Cr@UTM", "4057327": "a`zsDdrmuNwDrKe@|@o@z@u@p@u@f@u@\\cAXmMrCgA^m@Zy@j@sA`B", "4073043": "q_}sDpepuNbD?", "4056787": "uk~sDjymuNIW?sAH_@", "4072975": "ml~sDv}quNoC@gFA}BUsFA", "4077135": "m{{sDrtquNrBq@z@Q|BCjJj@", "4049791": "qtzsDnfluNb@fB", "4105983": "}f~sDpjjuNgC?", "4057887": "kl~sDndpuNGVA`@HT", "4040963": "{gatDntquNa@EiJCeP?eIA{D@", "4076999": "qk~sDttluNAoQ{JAkDBmBAuADaGAiMB", "4073075": "_j}sDrqmuNiJB", "4017931": "ilzsDljjuNnA@", "4097107": "wb_tDvfouN?wBxDBbD?@f@FV|A@", "4017935": "ikzsD|kjuNn@m@", "4066975": "}a|sDv{puNgAJc@@kIDgDE}AM", "4057963": "{d}sDv`puN?~K", "4057475": "kl~sDhqpuNFZ?l@GX", "4080307": "yj{sD~{puNCdBFbDVnBhB|J", "4080447": "oz{sDfyquNo@kC", "4040983": "{d}sDv`puNfDA", "4057371": "oz}sD`riuN`Wgn@", "4061059": "_r`tDp~iuNhNjInDnBlAj@b@^", "4057547": "ma~sDhgouNLDDA", "4056863": "_c_tDz}juN[EyA{@Y]", "4105935": "yk~sDl|guNApCAhJ@|b@", "4017955": "ilzsDljjuNT\\HP", "4066659": "iz}sD|xiuNE{E", "4056871": "_c_tDz}juNnBlA", "4057899": "ep~sDhbnuNaC@", "4056879": "ctbtDxqhuNtl@z]", "4097067": "mt~sDttnuNDmG?{H", "4056883": "mfatDtpiuN?Z", "4057275": "ka~sD~qmuN?_IFgHPyEPqCFuB?iNG_F?eJ", "4067027": "y{`tDd_nuNA~KmJ@A{F@iD", "4057911": "yz~sDpckuN`FtC", "4057923": "ut`tDr}iuNLJ", "4044603": "ev}sDz{puNtAMdB?`I?r@J", "4059287": "ep~sDhbnuNE|H?lG", "4057531": "qa~sDlfouNg@J", "4044607": "ev}sDz{puNtAFfL@r@K", "4066891": "i}|sDx{puNlDA", "4044611": "aoatDtzpuNe@JcC?a@K", "4078723": "iz}sD|xiuN?rP", "4057787": "{s`tDh}iuNKT", "4044615": "aoatDtzpuNe@IeAA}@@a@H", "4066635": "{h`tDrdiuNn@L", "4062079": "{`~sDvnpuNC`L", "4056911": "qe{sDpoluNoGjC_KrD{D|AwIrD", "4075791": "{x_tDdbnuNAdICv@a@jEEvAArM@b@", "4080311": "utbtDj`muN~ADXDn@Pz@XzHfDdFbCv@ZbAZz@NhBNtEHnDA", "4044115": "gubtDrzpuNx^@", "4101535": "gf{sDbrnuNqCq@aG_Bb@}D{BSQCSOYUmAyAeGeGw@cAIQCUNkAAm@Ge@w@sBuCqK", "4057259": "g_}sDjkruNA|FC~A?tI", "4077087": "ay_tDbeiuNCuM@gMC{CB{C", "4057907": "ws~sDfhkuN^d@pAv@xB`Af@LlBLtF@", "4057231": "aa~sDrdouNKr@CD", "4040543": "kg`tD`eiuNlAAvADbHA", "4056931": "ca~sDpkouNFO@sB", "4097111": "yj{sD~{puNuAEcCAiO?", "4026043": "ga~sDhbnuNCiO", "4056935": "ca~sDpkouNGQ@wAC]", "4044139": "ud~sDx{puNeAJoD?", "4044143": "}r~sDh{puNn@N`DJ", "4044147": "ml~sDv}quN?yY@wE", "4057243": "ou{sDneruNQF", "4044151": "il~sDl{puNAV", "4105939": "{k~sDfpiuNAdYVB", "4057891": "a`zsDdrmuNqNiHqA{@gBuAsAoAmB}Bk@{@uGmK", "4044155": "gc_tDb{puNkJE", "4057499": "kt`tD||iuNl@yA", "4056783": "sk~sDjbnuNA_H", "4044159": "}r~sDh{puNaDCgJA", "4066859": "uv}sDdaruNAlCE|C?fQ", "4044163": "gc_tDb{puNErIEhDCvG?dH", "4085443": "g_}sDjkruN@kT", "4073863": "mz|sDpepuNlG@mAkLeJ@", "4078699": "iz}sDpjjuNfTB", "4017815": "{}}sDp}quNAsF", "4066723": "}h`tDheiuNp@G", "4057295": "_`~sDdnkuN?[", "4057667": "gt~sDjbnuNob@@SAOE", "4057227": "aa~sDrdouNHp@FJ@FAHIH", "4066979": "}a|sDv{puNgAIiAAsK?y@?}AJ", "4077079": "yy_tD|aluNAmFFuj@", "4066711": "}f~sDpjjuN~GuPrB@", "4044187": "ca~sDpkouND|S", "4069611": "w{{sDpasuN]yAeAsDGa@?WBe@ZeBFo@?i@OgBAqE", "4057503": "ut`tDr}iuNHU", "4080431": "yuusDvlquNcMaAiKeA{Gk@__AuHkDSqCIwFAuz@@iCO", "4056731": "qk~sDttluNHr@@tJEbII\\", "4057511": "kt`tD||iuNNJ", "4097071": "qt~sDdeouNBoO", "4057927": "ut`tDr}iuNwPaK", "4061103": "_j}sDdsmuNJE", "4041651": "kz_tDlbluNFJF@JCBI", "4080551": "e_}sD~uquNfHA|Ht@PANC\\[dAi@u@eCbIoDjBhH", "4053943": "iu}sDdbnuN}JB", "4057467": "kl~sDltpuN@~E", "4057535": "yb~sDxfouNmHA", "4066827": "_y_tDfpiuNAcJ", "4065071": "sa}sDlqmuNkGD", "4057163": "yz~sDpckuNU[yA}@e@M", "4057331": "m{{sDrtquNQF", "4077035": "ia{sDrfsuNx@}ODmBE{AOcBy@kGyCcO", "4018047": "sa}sDlqmuN@i@", "4042187": "{d}sDvmpuNo@BkNB", "4061099": "_j}sDrqmuN?p@", "4042191": "wu}sD~`puNA_CBeDPkCBiBAcZGyQ", "4106023": "ak~sDdpiuNBoGCoFBe^BqC", "4057507": "kt`tD||iuNk@[", "4066591": "i}|sDx{puN]VMROj@", "4057559": "ou{sDneruN}D{O", "4066639": "}h`tDheiuN@U", "4106683": "uk~sD~tmuNA}A", "4041391": "wi}sDzuquNpIB", "4077059": "mt}sDlnkuN@lMEnV@jICvBObBG|A@dH", "4099039": "yj{sD~{puNhCQz_A?bFHhF^hr@rFxRdB|\\lCz@FbAB", "4080723": "iz_tD~fouN~D@~DIpJ?", "4061155": "mi}sD|tmuNQiB", "4069619": "uv}sDdaruNC}@", "4044455": "ev}sDz{puNyIA", "4061083": "un`tDvtiuN_@\\e@r@gAlC", "4059119": "{x_tDzzpuN\\?", "4068071": "un`tDvtiuNvBcBTWL_@Fc@@}ACcBDwAFEFM", "4057895": "ep~sDhbnuNpC@", "4080919": "{}}sDp}quNlD?LDZ\\HP", "4056915": "qtzsDnfluN_P`H", "4099359": "ol~sDr|ruN@{]", "4077007": "o}|sDlkmuNrAe@dOcG", "4057111": "agatDfbluNAzIBnDEzZ", "4040699": "yy_tD|aluNI@GL", "4025855": "wu}sD~mpuN?_L"}, "api_version": "1.2"}